[
  { "id": "loading_general_001", "category": "all", "text": "你的脑内正在请求一次检定……" },
  { "id": "loading_general_002", "category": "all", "text": "技能正在苏醒……" },
  { "id": "loading_general_003", "category": "all", "text": "骰子正在桌下发出不道德的声音……" },
  { "id": "loading_general_004", "category": "all", "text": "某个念头拒绝对此负责……" },
  { "id": "loading_general_005", "category": "all", "text": "逻辑正在整理证据。欲望正在吃掉证据。" },
  { "id": "loading_general_006", "category": "all", "text": "命运把手伸进口袋，摸出两枚骰子。" },
  { "id": "loading_general_007", "category": "all", "text": "一项非常不可靠的判断正在形成……" },
  { "id": "loading_general_008", "category": "all", "text": "系统正在区分直觉、借口和精神噪声……" },
  { "id": "loading_general_009", "category": "all", "text": "某种结论正在黑暗中穿鞋。" },
  { "id": "loading_general_010", "category": "all", "text": "当前状态尚未决定。" },
  { "id": "loading_food_001", "category": "food", "text": "电化学已经闻到了油脂。" },
  { "id": "loading_food_002", "category": "food", "text": "逻辑试图阻止，但它太饿了。" },
  { "id": "loading_food_003", "category": "food", "text": "胃部提交了一份措辞激烈的申请。" },
  { "id": "loading_food_004", "category": "food", "text": "夜晚正在提高所有碳水的说服力。" },
  { "id": "loading_social_001", "category": "social", "text": "镇定正在练习微笑。" },
  { "id": "loading_social_002", "category": "social", "text": "暗示正在排练一句听起来不尴尬的话。" },
  { "id": "loading_social_003", "category": "social", "text": "共情正在试图理解别人。它已经开始累了。" },
  { "id": "loading_work_001", "category": "work_study", "text": "意志力正在从地板上爬起来。" },
  { "id": "loading_work_002", "category": "work_study", "text": "逻辑打开了一个过于清醒的表格。" },
  { "id": "loading_work_003", "category": "work_study", "text": "任务正在角落里长出牙齿。" },
  { "id": "loading_absurd_001", "category": "absurd", "text": "系统读懂了。也可能没有。" },
  { "id": "loading_absurd_002", "category": "absurd", "text": "内陆帝国要求独自处理这个输入。" },
  { "id": "loading_absurd_003", "category": "absurd", "text": "这句话正在变成一只小型动物。" }
]
